{"type":"FeatureCollection","features":[{"type":"Feature","properties":{"title":"Tree","desc":"tree next to moffit","type":"nature"},"geometry":{"type":"Point","coordinates":[-122.26123,37.872146]}},{"type":"Feature","properties":{"title":"Blackberry","desc":"blackberry bush next to strawberry creek","type":"nature"},"geometry":{"type":"Point","coordinates":[-122.26212,37.872431]}},{"type":"Feature","properties":{"title":"University House","desc":"office of chancellor","type":"space"},"geometry":{"type":"Point","coordinates":[-122.26225,37.8745]}}]}